{
   "frames":{
      "bat_idle0.png":{
         "frame":{
            "x":0,
            "y":0,
            "w":64,
            "h":64
         },
         "rotated":false,
         "trimmed":false,
         "spriteSourceSize":{
            "x":0,
            "y":0,
            "w":64,
            "h":64
         },
         "sourceSize":{
            "w":64,
            "h":64
         }
      },
      "bat_idle1.png":{
         "frame":{
            "x":64,
            "y":0,
            "w":64,
            "h":64
         },
         "rotated":false,
         "trimmed":false,
         "spriteSourceSize":{
            "x":0,
            "y":0,
            "w":64,
            "h":64
         },
         "sourceSize":{
            "w":64,
            "h":64
         }
      },
      "bat_idle2.png":{
         "frame":{
            "x":0,
            "y":64,
            "w":64,
            "h":64
         },
         "rotated":false,
         "trimmed":false,
         "spriteSourceSize":{
            "x":0,
            "y":0,
            "w":64,
            "h":64
         },
         "sourceSize":{
            "w":64,
            "h":64
         }
      },
      "bat_idle3.png":{
         "frame":{
            "x":64,
            "y":64,
            "w":64,
            "h":64
         },
         "rotated":false,
         "trimmed":false,
         "spriteSourceSize":{
            "x":0,
            "y":0,
            "w":64,
            "h":64
         },
         "sourceSize":{
            "w":64,
            "h":64
         }
      },
      "bat_idle4.png":{
         "frame":{
            "x":0,
            "y":128,
            "w":64,
            "h":64
         },
         "rotated":false,
         "trimmed":false,
         "spriteSourceSize":{
            "x":0,
            "y":0,
            "w":64,
            "h":64
         },
         "sourceSize":{
            "w":64,
            "h":64
         }
      },
      "bat_idle5.png":{
         "frame":{
            "x":64,
            "y":128,
            "w":64,
            "h":64
         },
         "rotated":false,
         "trimmed":false,
         "spriteSourceSize":{
            "x":0,
            "y":0,
            "w":64,
            "h":64
         },
         "sourceSize":{
            "w":64,
            "h":64
         }
      }
   },
   "meta":{
      "app":"https://github.com/piskelapp/piskel/",
      "version":"1.0",
      "image":"bat_idle.png",
      "format":"RGBA8888",
      "size":{
         "w":128,
         "h":192
      }
   }
}
